nucleation-0.1.142.dist-info/METADATA
nucleation-0.1.142.dist-info/WHEEL
nucleation-0.1.142.dist-info/licenses/LICENSE
nucleation.pyi
nucleation/__init__.py
nucleation/__init__.pyi
nucleation/nucleation.cpython-312-x86_64-linux-gnu.so
nucleation/py.typed
py.typed
nucleation-0.1.142.dist-info/RECORD
