Metadata-Version: 2.4
Name: nucleation
Version: 0.1.142
Classifier: Development Status :: 4 - Beta
Classifier: Intended Audience :: Developers
Classifier: License :: OSI Approved :: GNU Affero General Public License v3
Classifier: Programming Language :: Python :: 3
Classifier: Programming Language :: Python :: 3.8
Classifier: Programming Language :: Python :: 3.9
Classifier: Programming Language :: Python :: 3.10
Classifier: Programming Language :: Python :: 3.11
Classifier: Programming Language :: Python :: 3.12
Classifier: Programming Language :: Rust
Classifier: Topic :: Games/Entertainment :: Simulation
Classifier: Topic :: Software Development :: Libraries :: Python Modules
License-File: LICENSE
Summary: A high-performance Minecraft schematic parser and utility library
Keywords: minecraft,schematic,parser,voxel
Author-email: Nano <nano@schem.at>
License: AGPL-3.0-only
Requires-Python: >=3.8
